[{
        "title": "Module 1 Unit 1 She was a driver before",
        "singer": "外研社五下",
        "cover": "http://ting.xiai123.com/images/wysyy5x.png",
        "src": "http://ting.xiai123.com/mp3/kewen/wysyy5x/Module 1 Unit 1 She was a driver before.mp3"
    },
    {
        "title": "Module 1 Unit 2 He worked in an office",
        "singer": "外研社五下",
        "cover": "http://ting.xiai123.com/images/wysyy5x.png",
        "src": "http://ting.xiai123.com/mp3/kewen/wysyy5x/Module 1 Unit 2 He worked in an office.mp3"
    },
    {
        "title": "Module 1 Words",
        "singer": "外研社五下",
        "cover": "http://ting.xiai123.com/images/wysyy5x.png",
        "src": "http://ting.xiai123.com/mp3/kewen/wysyy5x/Module 1 Words.mp3"
    },
    {
        "title": "Module 2 Unit 1 What did she have for lunch",
        "singer": "外研社五下",
        "cover": "http://ting.xiai123.com/images/wysyy5x.png",
        "src": "http://ting.xiai123.com/mp3/kewen/wysyy5x/Module 2 Unit 1 What did she have for lunch.mp3"
    },
    {
        "title": "Module 2 Unit 2 Lunch is usually at half past twelve",
        "singer": "外研社五下",
        "cover": "http://ting.xiai123.com/images/wysyy5x.png",
        "src": "http://ting.xiai123.com/mp3/kewen/wysyy5x/Module 2 Unit 2 Lunch is usually at half past twelve.mp3"
    },
    {
        "title": "Module 2 Words",
        "singer": "外研社五下",
        "cover": "http://ting.xiai123.com/images/wysyy5x.png",
        "src": "http://ting.xiai123.com/mp3/kewen/wysyy5x/Module 2 Words.mp3"
    },
    {
        "title": "Module 3 Unit 1 Have you got the Harry Potter DVDs",
        "singer": "外研社五下",
        "cover": "http://ting.xiai123.com/images/wysyy5x.png",
        "src": "http://ting.xiai123.com/mp3/kewen/wysyy5x/Module 3 Unit 1 Have you got the Harry Potter DVDs.mp3"
    },
    {
        "title": "Module 3 Unit 2 You can use the computers",
        "singer": "外研社五下",
        "cover": "http://ting.xiai123.com/images/wysyy5x.png",
        "src": "http://ting.xiai123.com/mp3/kewen/wysyy5x/Module 3 Unit 2 You can use the computers.mp3"
    },
    {
        "title": "Module 3 Words",
        "singer": "外研社五下",
        "cover": "http://ting.xiai123.com/images/wysyy5x.png",
        "src": "http://ting.xiai123.com/mp3/kewen/wysyy5x/Module 3 Words.mp3"
    },
    {
        "title": "Module 4 Unit 1 Did you read them",
        "singer": "外研社五下",
        "cover": "http://ting.xiai123.com/images/wysyy5x.png",
        "src": "http://ting.xiai123.com/mp3/kewen/wysyy5x/Module 4 Unit 1 Did you read them.mp3"
    },
    {
        "title": "Module 4 Unit 2 My favourite season is spring",
        "singer": "外研社五下",
        "cover": "http://ting.xiai123.com/images/wysyy5x.png",
        "src": "http://ting.xiai123.com/mp3/kewen/wysyy5x/Module 4 Unit 2 My favourite season is spring.mp3"
    },
    {
        "title": "Module 4 Words",
        "singer": "外研社五下",
        "cover": "http://ting.xiai123.com/images/wysyy5x.png",
        "src": "http://ting.xiai123.com/mp3/kewen/wysyy5x/Module 4 Words.mp3"
    },
    {
        "title": "Module 5 Unit 1 Your bag is broken",
        "singer": "外研社五下",
        "cover": "http://ting.xiai123.com/images/wysyy5x.png",
        "src": "http://ting.xiai123.com/mp3/kewen/wysyy5x/Module 5 Unit 1 Your bag is broken.mp3"
    },
    {
        "title": "Module 5 Unit 2 Mine is pink",
        "singer": "外研社五下",
        "cover": "http://ting.xiai123.com/images/wysyy5x.png",
        "src": "http://ting.xiai123.com/mp3/kewen/wysyy5x/Module 5 Unit 2 Mine is pink.mp3"
    },
    {
        "title": "Module 5 Words",
        "singer": "外研社五下",
        "cover": "http://ting.xiai123.com/images/wysyy5x.png",
        "src": "http://ting.xiai123.com/mp3/kewen/wysyy5x/Module 5 Words.mp3"
    },
    {
        "title": "Module 6 Unit 1 We’ll see lots of very big stones",
        "singer": "外研社五下",
        "cover": "http://ting.xiai123.com/images/wysyy5x.png",
        "src": "http://ting.xiai123.com/mp3/kewen/wysyy5x/Module 6 Unit 1 We’ll see lots of very big stones.mp3"
    },
    {
        "title": "Module 6 Unit 2 It was amazing",
        "singer": "外研社五下",
        "cover": "http://ting.xiai123.com/images/wysyy5x.png",
        "src": "http://ting.xiai123.com/mp3/kewen/wysyy5x/Module 6 Unit 2 It was amazing.mp3"
    },
    {
        "title": "Module 6 Words",
        "singer": "外研社五下",
        "cover": "http://ting.xiai123.com/images/wysyy5x.png",
        "src": "http://ting.xiai123.com/mp3/kewen/wysyy5x/Module 6 Words.mp3"
    },
    {
        "title": "Module 7 Unit 1 My father goes to work at 8 o’clock every morning",
        "singer": "外研社五下",
        "cover": "http://ting.xiai123.com/images/wysyy5x.png",
        "src": "http://ting.xiai123.com/mp3/kewen/wysyy5x/Module 7 Unit 1 My father goes to work at 8 o’clock every morning.mp3"
    },
    {
        "title": "Module 7 Unit 2 I’ll be home at 7 o’clock",
        "singer": "外研社五下",
        "cover": "http://ting.xiai123.com/images/wysyy5x.png",
        "src": "http://ting.xiai123.com/mp3/kewen/wysyy5x/Module 7 Unit 2 I’ll be home at 7 o’clock.mp3"
    },
    {
        "title": "Module 7 Words",
        "singer": "外研社五下",
        "cover": "http://ting.xiai123.com/images/wysyy5x.png",
        "src": "http://ting.xiai123.com/mp3/kewen/wysyy5x/Module 7 Words.mp3"
    },
    {
        "title": "Module 8 Unit 1 Will you help me",
        "singer": "外研社五下",
        "cover": "http://ting.xiai123.com/images/wysyy5x.png",
        "src": "http://ting.xiai123.com/mp3/kewen/wysyy5x/Module 8 Unit 1 Will you help me.mp3"
    },
    {
        "title": "Module 8 Unit 2 I made a kite",
        "singer": "外研社五下",
        "cover": "http://ting.xiai123.com/images/wysyy5x.png",
        "src": "http://ting.xiai123.com/mp3/kewen/wysyy5x/Module 8 Unit 2 I made a kite.mp3"
    },
    {
        "title": "Module 8 Words",
        "singer": "外研社五下",
        "cover": "http://ting.xiai123.com/images/wysyy5x.png",
        "src": "http://ting.xiai123.com/mp3/kewen/wysyy5x/Module 8 Words.mp3"
    },
    {
        "title": "Module 9 Unit 1 We laughed a lot",
        "singer": "外研社五下",
        "cover": "http://ting.xiai123.com/images/wysyy5x.png",
        "src": "http://ting.xiai123.com/mp3/kewen/wysyy5x/Module 9 Unit 1 We laughed a lot.mp3"
    },
    {
        "title": "Module 9 Unit 2 Mum bought new chopsticks for you",
        "singer": "外研社五下",
        "cover": "http://ting.xiai123.com/images/wysyy5x.png",
        "src": "http://ting.xiai123.com/mp3/kewen/wysyy5x/Module 9 Unit 2 Mum bought new chopsticks for you.mp3"
    },
    {
        "title": "Module 9 Words",
        "singer": "外研社五下",
        "cover": "http://ting.xiai123.com/images/wysyy5x.png",
        "src": "http://ting.xiai123.com/mp3/kewen/wysyy5x/Module 9 Words.mp3"
    },
    {
        "title": "Module 10 Unit 1 What did you put in your bag",
        "singer": "外研社五下",
        "cover": "http://ting.xiai123.com/images/wysyy5x.png",
        "src": "http://ting.xiai123.com/mp3/kewen/wysyy5x/Module 10 Unit 1 What did you put in your bag.mp3"
    },
    {
        "title": "Module 10 Unit 2 I played on the beach",
        "singer": "外研社五下",
        "cover": "http://ting.xiai123.com/images/wysyy5x.png",
        "src": "http://ting.xiai123.com/mp3/kewen/wysyy5x/Module 10 Unit 2 I played on the beach.mp3"
    },
    {
        "title": "Module 10 Words",
        "singer": "外研社五下",
        "cover": "http://ting.xiai123.com/images/wysyy5x.png",
        "src": "http://ting.xiai123.com/mp3/kewen/wysyy5x/Module 10 Words.mp3"
    },
    {
        "title": "Readming for pleasure",
        "singer": "外研社五下",
        "cover": "http://ting.xiai123.com/images/wysyy5x.png",
        "src": "http://ting.xiai123.com/mp3/kewen/wysyy5x/Readming for pleasure.mp3"
    },
    {
        "title": "Review Module Unit 2",
        "singer": "外研社五下",
        "cover": "http://ting.xiai123.com/images/wysyy5x.png",
        "src": "http://ting.xiai123.com/mp3/kewen/wysyy5x/Review Module Unit 2.mp3"
    }
]